CHANGELOG.txt
INSTALL.txt
LICENSE.txt
MANIFEST.in
README.txt
README.txt~
TODO.txt
example1.html
setup.cfg
setup.py
docs/build/html.zip
docs/build/doctrees/AutoDoc.doctree
docs/build/doctrees/TODO.doctree
docs/build/doctrees/environment.pickle
docs/build/doctrees/example.doctree
docs/build/doctrees/getting_started.doctree
docs/build/doctrees/index.doctree
docs/build/doctrees/installation.doctree
docs/build/doctrees/installation_bk.doctree
docs/build/doctrees/parameter_description.doctree
docs/build/doctrees/notused/AutoDoc.doctree
docs/build/doctrees/notused/getting_started.doctree
docs/build/doctrees/notused/installation_bk.doctree
docs/build/html/.buildinfo
docs/build/html/TODO.html
docs/build/html/genindex.html
docs/build/html/index.html
docs/build/html/installation.html
docs/build/html/objects.inv
docs/build/html/search.html
docs/build/html/searchindex.js
docs/build/html/_sources/TODO.txt
docs/build/html/_sources/index.txt
docs/build/html/_sources/installation.txt
docs/build/html/_static/ajax-loader.gif
docs/build/html/_static/basic.css
docs/build/html/_static/candle1.png
docs/build/html/_static/candle2.png
docs/build/html/_static/candle3.png
docs/build/html/_static/comment-bright.png
docs/build/html/_static/comment-close.png
docs/build/html/_static/comment.png
docs/build/html/_static/contents.png
docs/build/html/_static/doctools.js
docs/build/html/_static/down-pressed.png
docs/build/html/_static/down.png
docs/build/html/_static/file.png
docs/build/html/_static/jquery.js
docs/build/html/_static/light_cones_2D_and_3D.png
docs/build/html/_static/minus.png
docs/build/html/_static/navigation.png
docs/build/html/_static/plus.png
docs/build/html/_static/pygments.css
docs/build/html/_static/searchtools.js
docs/build/html/_static/sphinxdoc.css
docs/build/html/_static/test.h5
docs/build/html/_static/test_movie.avi
docs/build/html/_static/underscore.js
docs/build/html/_static/up-pressed.png
docs/build/html/_static/up.png
docs/build/html/_static/websupport.js
pyLICORS.egg-info/PKG-INFO
pyLICORS.egg-info/SOURCES.txt
pyLICORS.egg-info/dependency_links.txt
pyLICORS.egg-info/not-zip-safe
pyLICORS.egg-info/requires.txt
pyLICORS.egg-info/top_level.txt
