Metadata-Version: 1.1
Name: pyLICORS
Version: 0.0.1dev
Summary: A Python interface for predictive state estimation from spatio-temporal data
Home-page: www.stat.cmu.edu/~gmg
Author: Georg M. Goerg
Author-email: my_three_initials@stat.cmu.edu
License: GPLv3
Keywords: forecasting spatio-temporal nonparametric statistics estimation
Platform: UNKNOWN
Classifier: Development Status :: 1 - Planning
Classifier: Environment :: Console
Classifier: Intended Audience :: Science/Research
Classifier: License :: OSI Approved :: GNU General Public License v3 (GPLv3)
Classifier: Operating System :: OS Independent
Classifier: Programming Language :: Python :: 2.7
Classifier: Topic :: Scientific/Engineering
